verbatim_processor/__init__.py
verbatim_processor/project.py
verbatim_processor/enrichment/__init__.py
verbatim_processor/enrichment/classifier.py
verbatim_processor/enrichment/kairntech_task.py
verbatim_processor/enrichment/sentencizer.py
verbatim_processor/helpers/__init__.py
verbatim_processor/helpers/bootstrap_meta.py
verbatim_processor/helpers/chunk.py
verbatim_processor/helpers/processors_list.py
verbatim_processor/kairntech/__init__.py
verbatim_processor/kairntech/annotator.py
verbatim_processor/kairntech/client.py
verbatim_processor/pcx/__init__.py
verbatim_processor/pcx/push_pcx_task.py
verbatim_processor/pipeline/__init__.py
verbatim_processor/pipeline/pipeline.py
verbatim_processor/pipeline/task.py
verbatim_processor/pipeline/task_runner.py
verbatim_processor/pre_processing/__init__.py
verbatim_processor/pre_processing/file_processor.py
verbatim_processor/pre_processing/meta_column.py
verbatim_processor/processors/__init__.py
verbatim_processor/processors/processors.py
verbatim_processor/processors/recoder.py
pcx_utilities-0.1.2.dist-info/METADATA
pcx_utilities-0.1.2.dist-info/WHEEL
pcx_utilities-0.1.2.dist-info/top_level.txt
pcx_utilities-0.1.2.dist-info/RECORD
