Metadata-Version: 2.1
Name: pcx-utilities
Version: 0.1.2
Summary: A package to easily create pipeline for bva-cx-insights.com
Home-page: https://bva-cx-insights.com
Author: Adrien Liard
Author-email: adrien.liard@bva-group.com
License: MIT
Platform: UNKNOWN
Classifier: Programming Language :: Python :: 3
Classifier: Programming Language :: Python :: 3.6
Requires-Dist: pandas
Requires-Dist: requests
Requires-Dist: spacy
Requires-Dist: xlrd
Requires-Dist: openpyxl
